allspark/__init__.py
allspark/allspark.py
allspark/commands/__init__.py
allspark/commands/cmd_config.py
allspark/commands/cmd_init.py
allspark/commands/cmd_nuke.py
allspark/commands/cmd_proxy.py
allspark/commands/cmd_sparks.py
allspark/commands/cmd_update.py
allspark/commands/cmd_version.py
allspark/core/__init__.py
allspark/core/analytics.py
allspark/core/cache.py
allspark/core/clipboard.py
allspark/core/config.py
allspark/core/context.py
allspark/core/logger.py
allspark/core/randomness.py
allspark/core/stopwatch.py
allspark/core/util.py
allspark/providers/__init__.py
allspark/providers/api.py
allspark/providers/state.py
allspark/providers/azurerm/__init__.py
allspark/providers/azurerm/main.tf.tpl
allspark/providers/azurerm/sparks.json
allspark/providers/azurerm/terraform.tfvars.tpl
allspark/providers/azurerm/variables.tf.tpl
allspark/providers/common/__init__.py
allspark/providers/common/allsparks.yml.tpl
allspark/providers/common/ansible.cfg.tpl
allspark/providers/common/site.yml.tpl
allspark/providers/common/sparks.tf.tpl
allspark/providers/common/ssh_config.tpl
allspark-0.1.3.dist-info/DESCRIPTION.rst
allspark-0.1.3.dist-info/METADATA
allspark-0.1.3.dist-info/RECORD
allspark-0.1.3.dist-info/WHEEL
allspark-0.1.3.dist-info/entry_points.txt
allspark-0.1.3.dist-info/metadata.json
allspark-0.1.3.dist-info/top_level.txt
