Metadata-Version: 2.0
Name: allspark
Version: 0.1.3
Summary: AllSpark CLI
Home-page: https://github.com/broomyocymru/allspark
Author: Ant Broome
Author-email: broomyocymru@hotmail.com
License: MIT
Download-URL: https://github.com/broomyocymru/allspark/archive/0.1.3.tar.gz
Platform: any
Classifier: Development Status :: 3 - Alpha
Classifier: License :: OSI Approved :: MIT License
Classifier: Programming Language :: Python :: 2.7
Requires-Dist: ansible (>=2.2.1.0)
Requires-Dist: click (>=6.6)
Requires-Dist: colorama (>=0.3.7)
Requires-Dist: jinja2 (>=2.9.5)
Requires-Dist: jsonmerge (>=1.1.0)
Requires-Dist: jsonschema (>=2.5.1)
Requires-Dist: keyring (>=9.0)
Requires-Dist: oauthlib (>=0.7.2)
Requires-Dist: pywinrm (>=0.2.2)
Requires-Dist: pyyaml (>=3.12)
Requires-Dist: requests (>=2.9.1)
Requires-Dist: requests-oauthlib (>=0.5.0)
Requires-Dist: requests-toolbelt (>=0.4.0)
Requires-Dist: tlslite (>=0.4.8)
Requires-Dist: vcversioner (>=2.14.0.0)
